dbcl/__init__.py
dbcl/command_line.py
dbcl-0.1.27.dist-info/WHEEL
dbcl-0.1.27.dist-info/LICENSE.txt
dbcl-0.1.27.dist-info/METADATA
dbcl-0.1.27.dist-info/entry_points.txt
dbcl-0.1.27.dist-info/RECORD
