Metadata-Version: 2.1
Name: dbcl
Version: 0.1.27
Summary: A database command line interface that is engine-agnostic.
License: MIT
Author: Kris Steinhoff
Author-email: ksteinhoff@gmail.com
Requires-Python: >=3.8,<4.0
Classifier: License :: OSI Approved :: MIT License
Classifier: Programming Language :: Python :: 3
Classifier: Programming Language :: Python :: 3.8
Classifier: Programming Language :: Python :: 3.9
Classifier: Programming Language :: Python :: 3.10
Classifier: Programming Language :: Python :: 3.11
Requires-Dist: SQLAlchemy (>=1.4.46,<2.0.0)
Requires-Dist: prompt-toolkit (>=2.0.10,<3.0.0)
Requires-Dist: pygments (>=2.2.0,<3.0.0)
Requires-Dist: terminaltables (>=3.1.0,<4.0.0)
